aiologs/__init__.py
aiologs/esHandler.py
aiologs/mongoHandler.py
aiologs-0.0.8.dist-info/METADATA
aiologs-0.0.8.dist-info/WHEEL
aiologs-0.0.8.dist-info/top_level.txt
aiologs-0.0.8.dist-info/RECORD
