Metadata-Version: 2.1
Name: aiologs
Version: 0.0.8
Summary: ('修改支持关键信息不分词', '纯异步的高性能日志组件，支持日志保存文件、mongo、elasticsearch', 'Purely asynchronous high performance logging components，Support for writing files，mongo、elasticsearch')
Home-page: https://github.com/beincy/aiologs
Author: beincy
Author-email: bianhui0524@sina.com
Maintainer: 卞辉(beincy)
Maintainer-email: bianhui0524@sina.com
License: MIT
Platform: all
Classifier: Development Status :: 4 - Beta
Classifier: License :: OSI Approved :: MIT License
Classifier: Programming Language :: Python :: 3.5
Classifier: Programming Language :: Python :: 3.6
Classifier: Programming Language :: Python :: 3.7
Requires-Dist: uvloop
Requires-Dist: motor
Requires-Dist: elasticsearch-async
Requires-Dist: ujson
Requires-Dist: aiofiles
